{"nodes": [{"id": "d_project_mall_mall_admin_src_main_java_com_mall_admin_controller_merchant_merchantauthcontroller_java", "label": "MerchantAuthController.java", "file_type": "code", "source_file": "D:\\project\\mall\\mall-admin\\src\\main\\java\\com\\mall\\admin\\controller\\merchant\\MerchantAuthController.java", "source_location": "L1"}, {"id": "merchant_merchantauthcontroller_merchantauthcontroller", "label": "MerchantAuthController", "file_type": "code", "source_file": "D:\\project\\mall\\mall-admin\\src\\main\\java\\com\\mall\\admin\\controller\\merchant\\MerchantAuthController.java", "source_location": "L27"}, {"id": "merchant_merchantauthcontroller_merchantauthcontroller_login", "label": ".login()", "file_type": "code", "source_file": "D:\\project\\mall\\mall-admin\\src\\main\\java\\com\\mall\\admin\\controller\\merchant\\MerchantAuthController.java", "source_location": "L38"}, {"id": "merchant_merchantauthcontroller_merchantauthcontroller_info", "label": ".info()", "file_type": "code", "source_file": "D:\\project\\mall\\mall-admin\\src\\main\\java\\com\\mall\\admin\\controller\\merchant\\MerchantAuthController.java", "source_location": "L79"}, {"id": "merchant_merchantauthcontroller_merchantauthcontroller_logout", "label": ".logout()", "file_type": "code", "source_file": "D:\\project\\mall\\mall-admin\\src\\main\\java\\com\\mall\\admin\\controller\\merchant\\MerchantAuthController.java", "source_location": "L101"}, {"id": "merchant_merchantauthcontroller_merchantauthcontroller_extracttoken", "label": ".extractToken()", "file_type": "code", "source_file": "D:\\project\\mall\\mall-admin\\src\\main\\java\\com\\mall\\admin\\controller\\merchant\\MerchantAuthController.java", "source_location": "L108"}, {"id": "merchant_merchantauthcontroller_merchantauthcontroller_getclientip", "label": ".getClientIp()", "file_type": "code", "source_file": "D:\\project\\mall\\mall-admin\\src\\main\\java\\com\\mall\\admin\\controller\\merchant\\MerchantAuthController.java", "source_location": "L116"}], "edges": [{"source": "d_project_mall_mall_admin_src_main_java_com_mall_admin_controller_merchant_merchantauthcontroller_java", "target": "lambdaquerywrapper", "relation": "imports", "context": "import", "confidence": "EXTRACTED", "source_file": "D:\\project\\mall\\mall-admin\\src\\main\\java\\com\\mall\\admin\\controller\\merchant\\MerchantAuthController.java", "source_location": "L3", "weight": 1.0}, {"source": "d_project_mall_mall_admin_src_main_java_com_mall_admin_controller_merchant_merchantauthcontroller_java", "target": "rediskeyconstant", "relation": "imports", "context": "import", "confidence": "EXTRACTED", "source_file": "D:\\project\\mall\\mall-admin\\src\\main\\java\\com\\mall\\admin\\controller\\merchant\\MerchantAuthController.java", "source_location": "L4", "weight": 1.0}, {"source": "d_project_mall_mall_admin_src_main_java_com_mall_admin_controller_merchant_merchantauthcontroller_java", "target": "usertypeenum", "relation": "imports", "context": "import", "confidence": "EXTRACTED", "source_file": "D:\\project\\mall\\mall-admin\\src\\main\\java\\com\\mall\\admin\\controller\\merchant\\MerchantAuthController.java", "source_location": "L5", "weight": 1.0}, {"source": "d_project_mall_mall_admin_src_main_java_com_mall_admin_controller_merchant_merchantauthcontroller_java", "target": "businessexception", "relation": "imports", "context": "import", "confidence": "EXTRACTED", "source_file": "D:\\project\\mall\\mall-admin\\src\\main\\java\\com\\mall\\admin\\controller\\merchant\\MerchantAuthController.java", "source_location": "L6", "weight": 1.0}, {"source": "d_project_mall_mall_admin_src_main_java_com_mall_admin_controller_merchant_merchantauthcontroller_java", "target": "r", "relation": "imports", "context": "import", "confidence": "EXTRACTED", "source_file": "D:\\project\\mall\\mall-admin\\src\\main\\java\\com\\mall\\admin\\controller\\merchant\\MerchantAuthController.java", "source_location": "L7", "weight": 1.0}, {"source": "d_project_mall_mall_admin_src_main_java_com_mall_admin_controller_merchant_merchantauthcontroller_java", "target": "resultcode", "relation": "imports", "context": "import", "confidence": "EXTRACTED", "source_file": "D:\\project\\mall\\mall-admin\\src\\main\\java\\com\\mall\\admin\\controller\\merchant\\MerchantAuthController.java", "source_location": "L8", "weight": 1.0}, {"source": "d_project_mall_mall_admin_src_main_java_com_mall_admin_controller_merchant_merchantauthcontroller_java", "target": "jwtutil", "relation": "imports", "context": "import", "confidence": "EXTRACTED", "source_file": "D:\\project\\mall\\mall-admin\\src\\main\\java\\com\\mall\\admin\\controller\\merchant\\MerchantAuthController.java", "source_location": "L9", "weight": 1.0}, {"source": "d_project_mall_mall_admin_src_main_java_com_mall_admin_controller_merchant_merchantauthcontroller_java", "target": "passwordutil", "relation": "imports", "context": "import", "confidence": "EXTRACTED", "source_file": "D:\\project\\mall\\mall-admin\\src\\main\\java\\com\\mall\\admin\\controller\\merchant\\MerchantAuthController.java", "source_location": "L10", "weight": 1.0}, {"source": "d_project_mall_mall_admin_src_main_java_com_mall_admin_controller_merchant_merchantauthcontroller_java", "target": "ratelimitutil", "relation": "imports", "context": "import", "confidence": "EXTRACTED", "source_file": "D:\\project\\mall\\mall-admin\\src\\main\\java\\com\\mall\\admin\\controller\\merchant\\MerchantAuthController.java", "source_location": "L11", "weight": 1.0}, {"source": "d_project_mall_mall_admin_src_main_java_com_mall_admin_controller_merchant_merchantauthcontroller_java", "target": "tenantadminmapper", "relation": "imports", "context": "import", "confidence": "EXTRACTED", "source_file": "D:\\project\\mall\\mall-admin\\src\\main\\java\\com\\mall\\admin\\controller\\merchant\\MerchantAuthController.java", "source_location": "L12", "weight": 1.0}, {"source": "d_project_mall_mall_admin_src_main_java_com_mall_admin_controller_merchant_merchantauthcontroller_java", "target": "tenantadmin", "relation": "imports", "context": "import", "confidence": "EXTRACTED", "source_file": "D:\\project\\mall\\mall-admin\\src\\main\\java\\com\\mall\\admin\\controller\\merchant\\MerchantAuthController.java", "source_location": "L13", "weight": 1.0}, {"source": "d_project_mall_mall_admin_src_main_java_com_mall_admin_controller_merchant_merchantauthcontroller_java", "target": "loginvo", "relation": "imports", "context": "import", "confidence": "EXTRACTED", "source_file": "D:\\project\\mall\\mall-admin\\src\\main\\java\\com\\mall\\admin\\controller\\merchant\\MerchantAuthController.java", "source_location": "L14", "weight": 1.0}, {"source": "d_project_mall_mall_admin_src_main_java_com_mall_admin_controller_merchant_merchantauthcontroller_java", "target": "authservice", "relation": "imports", "context": "import", "confidence": "EXTRACTED", "source_file": "D:\\project\\mall\\mall-admin\\src\\main\\java\\com\\mall\\admin\\controller\\merchant\\MerchantAuthController.java", "source_location": "L15", "weight": 1.0}, {"source": "d_project_mall_mall_admin_src_main_java_com_mall_admin_controller_merchant_merchantauthcontroller_java", "target": "requiredargsconstructor", "relation": "imports", "context": "import", "confidence": "EXTRACTED", "source_file": "D:\\project\\mall\\mall-admin\\src\\main\\java\\com\\mall\\admin\\controller\\merchant\\MerchantAuthController.java", "source_location": "L16", "weight": 1.0}, {"source": "d_project_mall_mall_admin_src_main_java_com_mall_admin_controller_merchant_merchantauthcontroller_java", "target": "slf4j", "relation": "imports", "context": "import", "confidence": "EXTRACTED", "source_file": "D:\\project\\mall\\mall-admin\\src\\main\\java\\com\\mall\\admin\\controller\\merchant\\MerchantAuthController.java", "source_location": "L17", "weight": 1.0}, {"source": "d_project_mall_mall_admin_src_main_java_com_mall_admin_controller_merchant_merchantauthcontroller_java", "target": "annotation", "relation": "imports", "context": "import", "confidence": "EXTRACTED", "source_file": "D:\\project\\mall\\mall-admin\\src\\main\\java\\com\\mall\\admin\\controller\\merchant\\MerchantAuthController.java", "source_location": "L18", "weight": 1.0}, {"source": "d_project_mall_mall_admin_src_main_java_com_mall_admin_controller_merchant_merchantauthcontroller_java", "target": "httpservletrequest", "relation": "imports", "context": "import", "confidence": "EXTRACTED", "source_file": "D:\\project\\mall\\mall-admin\\src\\main\\java\\com\\mall\\admin\\controller\\merchant\\MerchantAuthController.java", "source_location": "L20", "weight": 1.0}, {"source": "d_project_mall_mall_admin_src_main_java_com_mall_admin_controller_merchant_merchantauthcontroller_java", "target": "localdatetime", "relation": "imports", "context": "import", "confidence": "EXTRACTED", "source_file": "D:\\project\\mall\\mall-admin\\src\\main\\java\\com\\mall\\admin\\controller\\merchant\\MerchantAuthController.java", "source_location": "L22", "weight": 1.0}, {"source": "d_project_mall_mall_admin_src_main_java_com_mall_admin_controller_merchant_merchantauthcontroller_java", "target": "merchant_merchantauthcontroller_merchantauthcontroller", "relation": "contains", "confidence": "EXTRACTED", "source_file": "D:\\project\\mall\\mall-admin\\src\\main\\java\\com\\mall\\admin\\controller\\merchant\\MerchantAuthController.java", "source_location": "L27", "weight": 1.0}, {"source": "merchant_merchantauthcontroller_merchantauthcontroller", "target": "merchant_merchantauthcontroller_merchantauthcontroller_login", "relation": "method", "confidence": "EXTRACTED", "source_file": "D:\\project\\mall\\mall-admin\\src\\main\\java\\com\\mall\\admin\\controller\\merchant\\MerchantAuthController.java", "source_location": "L38", "weight": 1.0}, {"source": "merchant_merchantauthcontroller_merchantauthcontroller", "target": "merchant_merchantauthcontroller_merchantauthcontroller_info", "relation": "method", "confidence": "EXTRACTED", "source_file": "D:\\project\\mall\\mall-admin\\src\\main\\java\\com\\mall\\admin\\controller\\merchant\\MerchantAuthController.java", "source_location": "L79", "weight": 1.0}, {"source": "merchant_merchantauthcontroller_merchantauthcontroller", "target": "merchant_merchantauthcontroller_merchantauthcontroller_logout", "relation": "method", "confidence": "EXTRACTED", "source_file": "D:\\project\\mall\\mall-admin\\src\\main\\java\\com\\mall\\admin\\controller\\merchant\\MerchantAuthController.java", "source_location": "L101", "weight": 1.0}, {"source": "merchant_merchantauthcontroller_merchantauthcontroller", "target": "merchant_merchantauthcontroller_merchantauthcontroller_extracttoken", "relation": "method", "confidence": "EXTRACTED", "source_file": "D:\\project\\mall\\mall-admin\\src\\main\\java\\com\\mall\\admin\\controller\\merchant\\MerchantAuthController.java", "source_location": "L108", "weight": 1.0}, {"source": "merchant_merchantauthcontroller_merchantauthcontroller", "target": "merchant_merchantauthcontroller_merchantauthcontroller_getclientip", "relation": "method", "confidence": "EXTRACTED", "source_file": "D:\\project\\mall\\mall-admin\\src\\main\\java\\com\\mall\\admin\\controller\\merchant\\MerchantAuthController.java", "source_location": "L116", "weight": 1.0}, {"source": "merchant_merchantauthcontroller_merchantauthcontroller_login", "target": "merchant_merchantauthcontroller_merchantauthcontroller_getclientip", "relation": "calls", "context": "call", "confidence": "EXTRACTED", "source_file": "D:\\project\\mall\\mall-admin\\src\\main\\java\\com\\mall\\admin\\controller\\merchant\\MerchantAuthController.java", "source_location": "L41", "weight": 1.0}, {"source": "merchant_merchantauthcontroller_merchantauthcontroller_logout", "target": "merchant_merchantauthcontroller_merchantauthcontroller_extracttoken", "relation": "calls", "context": "call", "confidence": "EXTRACTED", "source_file": "D:\\project\\mall\\mall-admin\\src\\main\\java\\com\\mall\\admin\\controller\\merchant\\MerchantAuthController.java", "source_location": "L103", "weight": 1.0}], "raw_calls": [{"caller_nid": "merchant_merchantauthcontroller_merchantauthcontroller_login", "callee": "checkRateLimit", "is_member_call": false, "source_file": "D:\\project\\mall\\mall-admin\\src\\main\\java\\com\\mall\\admin\\controller\\merchant\\MerchantAuthController.java", "source_location": "L43"}, {"caller_nid": "merchant_merchantauthcontroller_merchantauthcontroller_login", "callee": "selectOne", "is_member_call": false, "source_file": "D:\\project\\mall\\mall-admin\\src\\main\\java\\com\\mall\\admin\\controller\\merchant\\MerchantAuthController.java", "source_location": "L44"}, {"caller_nid": "merchant_merchantauthcontroller_merchantauthcontroller_login", "callee": "eq", "is_member_call": false, "source_file": "D:\\project\\mall\\mall-admin\\src\\main\\java\\com\\mall\\admin\\controller\\merchant\\MerchantAuthController.java", "source_location": "L45"}, {"caller_nid": "merchant_merchantauthcontroller_merchantauthcontroller_login", "callee": "getStatus", "is_member_call": false, "source_file": "D:\\project\\mall\\mall-admin\\src\\main\\java\\com\\mall\\admin\\controller\\merchant\\MerchantAuthController.java", "source_location": "L49"}, {"caller_nid": "merchant_merchantauthcontroller_merchantauthcontroller_login", "callee": "verify", "is_member_call": false, "source_file": "D:\\project\\mall\\mall-admin\\src\\main\\java\\com\\mall\\admin\\controller\\merchant\\MerchantAuthController.java", "source_location": "L52"}, {"caller_nid": "merchant_merchantauthcontroller_merchantauthcontroller_login", "callee": "getPassword", "is_member_call": false, "source_file": "D:\\project\\mall\\mall-admin\\src\\main\\java\\com\\mall\\admin\\controller\\merchant\\MerchantAuthController.java", "source_location": "L52"}, {"caller_nid": "merchant_merchantauthcontroller_merchantauthcontroller_login", "callee": "setLastLoginTime", "is_member_call": false, "source_file": "D:\\project\\mall\\mall-admin\\src\\main\\java\\com\\mall\\admin\\controller\\merchant\\MerchantAuthController.java", "source_location": "L57"}, {"caller_nid": "merchant_merchantauthcontroller_merchantauthcontroller_login", "callee": "now", "is_member_call": false, "source_file": "D:\\project\\mall\\mall-admin\\src\\main\\java\\com\\mall\\admin\\controller\\merchant\\MerchantAuthController.java", "source_location": "L57"}, {"caller_nid": "merchant_merchantauthcontroller_merchantauthcontroller_login", "callee": "updateById", "is_member_call": false, "source_file": "D:\\project\\mall\\mall-admin\\src\\main\\java\\com\\mall\\admin\\controller\\merchant\\MerchantAuthController.java", "source_location": "L58"}, {"caller_nid": "merchant_merchantauthcontroller_merchantauthcontroller_login", "callee": "generateToken", "is_member_call": false, "source_file": "D:\\project\\mall\\mall-admin\\src\\main\\java\\com\\mall\\admin\\controller\\merchant\\MerchantAuthController.java", "source_location": "L60"}, {"caller_nid": "merchant_merchantauthcontroller_merchantauthcontroller_login", "callee": "getId", "is_member_call": false, "source_file": "D:\\project\\mall\\mall-admin\\src\\main\\java\\com\\mall\\admin\\controller\\merchant\\MerchantAuthController.java", "source_location": "L60"}, {"caller_nid": "merchant_merchantauthcontroller_merchantauthcontroller_login", "callee": "getCode", "is_member_call": false, "source_file": "D:\\project\\mall\\mall-admin\\src\\main\\java\\com\\mall\\admin\\controller\\merchant\\MerchantAuthController.java", "source_location": "L60"}, {"caller_nid": "merchant_merchantauthcontroller_merchantauthcontroller_login", "callee": "getTenantId", "is_member_call": false, "source_file": "D:\\project\\mall\\mall-admin\\src\\main\\java\\com\\mall\\admin\\controller\\merchant\\MerchantAuthController.java", "source_location": "L60"}, {"caller_nid": "merchant_merchantauthcontroller_merchantauthcontroller_login", "callee": "generateRefreshToken", "is_member_call": false, "source_file": "D:\\project\\mall\\mall-admin\\src\\main\\java\\com\\mall\\admin\\controller\\merchant\\MerchantAuthController.java", "source_location": "L61"}, {"caller_nid": "merchant_merchantauthcontroller_merchantauthcontroller_login", "callee": "getId", "is_member_call": false, "source_file": "D:\\project\\mall\\mall-admin\\src\\main\\java\\com\\mall\\admin\\controller\\merchant\\MerchantAuthController.java", "source_location": "L61"}, {"caller_nid": "merchant_merchantauthcontroller_merchantauthcontroller_login", "callee": "getCode", "is_member_call": false, "source_file": "D:\\project\\mall\\mall-admin\\src\\main\\java\\com\\mall\\admin\\controller\\merchant\\MerchantAuthController.java", "source_location": "L61"}, {"caller_nid": "merchant_merchantauthcontroller_merchantauthcontroller_login", "callee": "getTenantId", "is_member_call": false, "source_file": "D:\\project\\mall\\mall-admin\\src\\main\\java\\com\\mall\\admin\\controller\\merchant\\MerchantAuthController.java", "source_location": "L61"}, {"caller_nid": "merchant_merchantauthcontroller_merchantauthcontroller_login", "callee": "setAccessToken", "is_member_call": false, "source_file": "D:\\project\\mall\\mall-admin\\src\\main\\java\\com\\mall\\admin\\controller\\merchant\\MerchantAuthController.java", "source_location": "L64"}, {"caller_nid": "merchant_merchantauthcontroller_merchantauthcontroller_login", "callee": "setRefreshToken", "is_member_call": false, "source_file": "D:\\project\\mall\\mall-admin\\src\\main\\java\\com\\mall\\admin\\controller\\merchant\\MerchantAuthController.java", "source_location": "L65"}, {"caller_nid": "merchant_merchantauthcontroller_merchantauthcontroller_login", "callee": "setUserId", "is_member_call": false, "source_file": "D:\\project\\mall\\mall-admin\\src\\main\\java\\com\\mall\\admin\\controller\\merchant\\MerchantAuthController.java", "source_location": "L68"}, {"caller_nid": "merchant_merchantauthcontroller_merchantauthcontroller_login", "callee": "getId", "is_member_call": false, "source_file": "D:\\project\\mall\\mall-admin\\src\\main\\java\\com\\mall\\admin\\controller\\merchant\\MerchantAuthController.java", "source_location": "L68"}, {"caller_nid": "merchant_merchantauthcontroller_merchantauthcontroller_login", "callee": "setUsername", "is_member_call": false, "source_file": "D:\\project\\mall\\mall-admin\\src\\main\\java\\com\\mall\\admin\\controller\\merchant\\MerchantAuthController.java", "source_location": "L69"}, {"caller_nid": "merchant_merchantauthcontroller_merchantauthcontroller_login", "callee": "getUsername", "is_member_call": false, "source_file": "D:\\project\\mall\\mall-admin\\src\\main\\java\\com\\mall\\admin\\controller\\merchant\\MerchantAuthController.java", "source_location": "L69"}, {"caller_nid": "merchant_merchantauthcontroller_merchantauthcontroller_login", "callee": "setNickname", "is_member_call": false, "source_file": "D:\\project\\mall\\mall-admin\\src\\main\\java\\com\\mall\\admin\\controller\\merchant\\MerchantAuthController.java", "source_location": "L70"}, {"caller_nid": "merchant_merchantauthcontroller_merchantauthcontroller_login", "callee": "getRealName", "is_member_call": false, "source_file": "D:\\project\\mall\\mall-admin\\src\\main\\java\\com\\mall\\admin\\controller\\merchant\\MerchantAuthController.java", "source_location": "L70"}, {"caller_nid": "merchant_merchantauthcontroller_merchantauthcontroller_login", "callee": "setUserType", "is_member_call": false, "source_file": "D:\\project\\mall\\mall-admin\\src\\main\\java\\com\\mall\\admin\\controller\\merchant\\MerchantAuthController.java", "source_location": "L71"}, {"caller_nid": "merchant_merchantauthcontroller_merchantauthcontroller_login", "callee": "getCode", "is_member_call": false, "source_file": "D:\\project\\mall\\mall-admin\\src\\main\\java\\com\\mall\\admin\\controller\\merchant\\MerchantAuthController.java", "source_location": "L71"}, {"caller_nid": "merchant_merchantauthcontroller_merchantauthcontroller_login", "callee": "setTenantId", "is_member_call": false, "source_file": "D:\\project\\mall\\mall-admin\\src\\main\\java\\com\\mall\\admin\\controller\\merchant\\MerchantAuthController.java", "source_location": "L72"}, {"caller_nid": "merchant_merchantauthcontroller_merchantauthcontroller_login", "callee": "getTenantId", "is_member_call": false, "source_file": "D:\\project\\mall\\mall-admin\\src\\main\\java\\com\\mall\\admin\\controller\\merchant\\MerchantAuthController.java", "source_location": "L72"}, {"caller_nid": "merchant_merchantauthcontroller_merchantauthcontroller_login", "callee": "setUserInfo", "is_member_call": false, "source_file": "D:\\project\\mall\\mall-admin\\src\\main\\java\\com\\mall\\admin\\controller\\merchant\\MerchantAuthController.java", "source_location": "L73"}, {"caller_nid": "merchant_merchantauthcontroller_merchantauthcontroller_login", "callee": "clearRateLimit", "is_member_call": false, "source_file": "D:\\project\\mall\\mall-admin\\src\\main\\java\\com\\mall\\admin\\controller\\merchant\\MerchantAuthController.java", "source_location": "L75"}, {"caller_nid": "merchant_merchantauthcontroller_merchantauthcontroller_login", "callee": "ok", "is_member_call": false, "source_file": "D:\\project\\mall\\mall-admin\\src\\main\\java\\com\\mall\\admin\\controller\\merchant\\MerchantAuthController.java", "source_location": "L76"}, {"caller_nid": "merchant_merchantauthcontroller_merchantauthcontroller_info", "callee": "getUserId", "is_member_call": false, "source_file": "D:\\project\\mall\\mall-admin\\src\\main\\java\\com\\mall\\admin\\controller\\merchant\\MerchantAuthController.java", "source_location": "L81"}, {"caller_nid": "merchant_merchantauthcontroller_merchantauthcontroller_info", "callee": "selectById", "is_member_call": false, "source_file": "D:\\project\\mall\\mall-admin\\src\\main\\java\\com\\mall\\admin\\controller\\merchant\\MerchantAuthController.java", "source_location": "L86"}, {"caller_nid": "merchant_merchantauthcontroller_merchantauthcontroller_info", "callee": "setUserId", "is_member_call": false, "source_file": "D:\\project\\mall\\mall-admin\\src\\main\\java\\com\\mall\\admin\\controller\\merchant\\MerchantAuthController.java", "source_location": "L92"}, {"caller_nid": "merchant_merchantauthcontroller_merchantauthcontroller_info", "callee": "getId", "is_member_call": false, "source_file": "D:\\project\\mall\\mall-admin\\src\\main\\java\\com\\mall\\admin\\controller\\merchant\\MerchantAuthController.java", "source_location": "L92"}, {"caller_nid": "merchant_merchantauthcontroller_merchantauthcontroller_info", "callee": "setUsername", "is_member_call": false, "source_file": "D:\\project\\mall\\mall-admin\\src\\main\\java\\com\\mall\\admin\\controller\\merchant\\MerchantAuthController.java", "source_location": "L93"}, {"caller_nid": "merchant_merchantauthcontroller_merchantauthcontroller_info", "callee": "getUsername", "is_member_call": false, "source_file": "D:\\project\\mall\\mall-admin\\src\\main\\java\\com\\mall\\admin\\controller\\merchant\\MerchantAuthController.java", "source_location": "L93"}, {"caller_nid": "merchant_merchantauthcontroller_merchantauthcontroller_info", "callee": "setNickname", "is_member_call": false, "source_file": "D:\\project\\mall\\mall-admin\\src\\main\\java\\com\\mall\\admin\\controller\\merchant\\MerchantAuthController.java", "source_location": "L94"}, {"caller_nid": "merchant_merchantauthcontroller_merchantauthcontroller_info", "callee": "getRealName", "is_member_call": false, "source_file": "D:\\project\\mall\\mall-admin\\src\\main\\java\\com\\mall\\admin\\controller\\merchant\\MerchantAuthController.java", "source_location": "L94"}, {"caller_nid": "merchant_merchantauthcontroller_merchantauthcontroller_info", "callee": "setAvatar", "is_member_call": false, "source_file": "D:\\project\\mall\\mall-admin\\src\\main\\java\\com\\mall\\admin\\controller\\merchant\\MerchantAuthController.java", "source_location": "L95"}, {"caller_nid": "merchant_merchantauthcontroller_merchantauthcontroller_info", "callee": "setUserType", "is_member_call": false, "source_file": "D:\\project\\mall\\mall-admin\\src\\main\\java\\com\\mall\\admin\\controller\\merchant\\MerchantAuthController.java", "source_location": "L96"}, {"caller_nid": "merchant_merchantauthcontroller_merchantauthcontroller_info", "callee": "getCode", "is_member_call": false, "source_file": "D:\\project\\mall\\mall-admin\\src\\main\\java\\com\\mall\\admin\\controller\\merchant\\MerchantAuthController.java", "source_location": "L96"}, {"caller_nid": "merchant_merchantauthcontroller_merchantauthcontroller_info", "callee": "setTenantId", "is_member_call": false, "source_file": "D:\\project\\mall\\mall-admin\\src\\main\\java\\com\\mall\\admin\\controller\\merchant\\MerchantAuthController.java", "source_location": "L97"}, {"caller_nid": "merchant_merchantauthcontroller_merchantauthcontroller_info", "callee": "getTenantId", "is_member_call": false, "source_file": "D:\\project\\mall\\mall-admin\\src\\main\\java\\com\\mall\\admin\\controller\\merchant\\MerchantAuthController.java", "source_location": "L97"}, {"caller_nid": "merchant_merchantauthcontroller_merchantauthcontroller_info", "callee": "ok", "is_member_call": false, "source_file": "D:\\project\\mall\\mall-admin\\src\\main\\java\\com\\mall\\admin\\controller\\merchant\\MerchantAuthController.java", "source_location": "L98"}, {"caller_nid": "merchant_merchantauthcontroller_merchantauthcontroller_logout", "callee": "ok", "is_member_call": false, "source_file": "D:\\project\\mall\\mall-admin\\src\\main\\java\\com\\mall\\admin\\controller\\merchant\\MerchantAuthController.java", "source_location": "L105"}, {"caller_nid": "merchant_merchantauthcontroller_merchantauthcontroller_extracttoken", "callee": "getHeader", "is_member_call": false, "source_file": "D:\\project\\mall\\mall-admin\\src\\main\\java\\com\\mall\\admin\\controller\\merchant\\MerchantAuthController.java", "source_location": "L109"}, {"caller_nid": "merchant_merchantauthcontroller_merchantauthcontroller_extracttoken", "callee": "startsWith", "is_member_call": false, "source_file": "D:\\project\\mall\\mall-admin\\src\\main\\java\\com\\mall\\admin\\controller\\merchant\\MerchantAuthController.java", "source_location": "L110"}, {"caller_nid": "merchant_merchantauthcontroller_merchantauthcontroller_extracttoken", "callee": "substring", "is_member_call": false, "source_file": "D:\\project\\mall\\mall-admin\\src\\main\\java\\com\\mall\\admin\\controller\\merchant\\MerchantAuthController.java", "source_location": "L111"}, {"caller_nid": "merchant_merchantauthcontroller_merchantauthcontroller_getclientip", "callee": "getHeader", "is_member_call": false, "source_file": "D:\\project\\mall\\mall-admin\\src\\main\\java\\com\\mall\\admin\\controller\\merchant\\MerchantAuthController.java", "source_location": "L117"}, {"caller_nid": "merchant_merchantauthcontroller_merchantauthcontroller_getclientip", "callee": "isEmpty", "is_member_call": false, "source_file": "D:\\project\\mall\\mall-admin\\src\\main\\java\\com\\mall\\admin\\controller\\merchant\\MerchantAuthController.java", "source_location": "L118"}, {"caller_nid": "merchant_merchantauthcontroller_merchantauthcontroller_getclientip", "callee": "equalsIgnoreCase", "is_member_call": false, "source_file": "D:\\project\\mall\\mall-admin\\src\\main\\java\\com\\mall\\admin\\controller\\merchant\\MerchantAuthController.java", "source_location": "L118"}, {"caller_nid": "merchant_merchantauthcontroller_merchantauthcontroller_getclientip", "callee": "trim", "is_member_call": false, "source_file": "D:\\project\\mall\\mall-admin\\src\\main\\java\\com\\mall\\admin\\controller\\merchant\\MerchantAuthController.java", "source_location": "L119"}, {"caller_nid": "merchant_merchantauthcontroller_merchantauthcontroller_getclientip", "callee": "split", "is_member_call": false, "source_file": "D:\\project\\mall\\mall-admin\\src\\main\\java\\com\\mall\\admin\\controller\\merchant\\MerchantAuthController.java", "source_location": "L119"}, {"caller_nid": "merchant_merchantauthcontroller_merchantauthcontroller_getclientip", "callee": "getRemoteAddr", "is_member_call": false, "source_file": "D:\\project\\mall\\mall-admin\\src\\main\\java\\com\\mall\\admin\\controller\\merchant\\MerchantAuthController.java", "source_location": "L121"}]}