{"nodes": [{"id": "d_project_mall_mall_admin_web_src_api_system_ts", "label": "system.ts", "file_type": "code", "source_file": "D:\\project\\mall\\mall-admin-web\\src\\api\\system.ts", "source_location": "L1"}, {"id": "api_system_getconfiglist", "label": "getConfigList()", "file_type": "code", "source_file": "D:\\project\\mall\\mall-admin-web\\src\\api\\system.ts", "source_location": "L17"}, {"id": "api_system_updateconfig", "label": "updateConfig()", "file_type": "code", "source_file": "D:\\project\\mall\\mall-admin-web\\src\\api\\system.ts", "source_location": "L21"}, {"id": "api_system_uploadfile", "label": "uploadFile()", "file_type": "code", "source_file": "D:\\project\\mall\\mall-admin-web\\src\\api\\system.ts", "source_location": "L25"}], "edges": [{"source": "d_project_mall_mall_admin_web_src_api_system_ts", "target": "d_project_mall_mall_admin_web_src_utils_request", "relation": "imports_from", "context": "import", "confidence": "EXTRACTED", "source_file": "D:\\project\\mall\\mall-admin-web\\src\\api\\system.ts", "source_location": "L1", "weight": 1.0}, {"source": "d_project_mall_mall_admin_web_src_api_system_ts", "target": "utils_request_request", "relation": "imports", "context": "import", "confidence": "EXTRACTED", "source_file": "D:\\project\\mall\\mall-admin-web\\src\\api\\system.ts", "source_location": "L1", "weight": 1.0}, {"source": "d_project_mall_mall_admin_web_src_api_system_ts", "target": "api_system_getconfiglist", "relation": "contains", "confidence": "EXTRACTED", "source_file": "D:\\project\\mall\\mall-admin-web\\src\\api\\system.ts", "source_location": "L17", "weight": 1.0}, {"source": "d_project_mall_mall_admin_web_src_api_system_ts", "target": "api_system_updateconfig", "relation": "contains", "confidence": "EXTRACTED", "source_file": "D:\\project\\mall\\mall-admin-web\\src\\api\\system.ts", "source_location": "L21", "weight": 1.0}, {"source": "d_project_mall_mall_admin_web_src_api_system_ts", "target": "api_system_uploadfile", "relation": "contains", "confidence": "EXTRACTED", "source_file": "D:\\project\\mall\\mall-admin-web\\src\\api\\system.ts", "source_location": "L25", "weight": 1.0}], "raw_calls": [{"caller_nid": "api_system_getconfiglist", "callee": "get", "is_member_call": true, "source_file": "D:\\project\\mall\\mall-admin-web\\src\\api\\system.ts", "source_location": "L18"}, {"caller_nid": "api_system_updateconfig", "callee": "put", "is_member_call": true, "source_file": "D:\\project\\mall\\mall-admin-web\\src\\api\\system.ts", "source_location": "L22"}, {"caller_nid": "api_system_uploadfile", "callee": "Number", "is_member_call": false, "source_file": "D:\\project\\mall\\mall-admin-web\\src\\api\\system.ts", "source_location": "L26"}, {"caller_nid": "api_system_uploadfile", "callee": "getItem", "is_member_call": true, "source_file": "D:\\project\\mall\\mall-admin-web\\src\\api\\system.ts", "source_location": "L26"}, {"caller_nid": "api_system_uploadfile", "callee": "append", "is_member_call": true, "source_file": "D:\\project\\mall\\mall-admin-web\\src\\api\\system.ts", "source_location": "L29"}, {"caller_nid": "api_system_uploadfile", "callee": "post", "is_member_call": true, "source_file": "D:\\project\\mall\\mall-admin-web\\src\\api\\system.ts", "source_location": "L30"}]}